wa/__init__.py
wa/models.py
wa/py.typed
wa/utils.py
wa/cli/__init__.py
wa/cli/__main__.py
wa/cli/options.py
wa/cli/utils.py
wa/cli/version.py
wa/data/__init__.py
wa/data/mcp/agent.md
wa/mcp/__init__.py
wa/mcp/__main__.py
wa/mcp/install.py
wa/mcp/types.py
wa/mcp/uninstall.py
wa/mcp/utils.py
wa/mcp/cli/__init__.py
wa/mcp/cli/__main__.py
wa/mcp/cli/development.py
wa/mcp/cli/install.py
wa/mcp/cli/uninstall.py
wa/workspace/__init__.py
wa/workspace/create.py
wa/workspace/delete.py
wa/workspace/list.py
wa/workspace/read.py
wa/workspace/cli/__init__.py
wa/workspace/cli/create.py
wa/workspace/cli/delete.py
wa/workspace/cli/list.py
wa/workspace/cli/read.py
wa/workspace/mcp/__init__.py
wa/workspace/mcp/resources.py
wa/workspace/mcp/tools.py
workspace_agent-0.1.4.dist-info/licenses/LICENSE
workspace_agent-0.1.4.dist-info/METADATA
workspace_agent-0.1.4.dist-info/WHEEL
workspace_agent-0.1.4.dist-info/entry_points.txt
workspace_agent-0.1.4.dist-info/top_level.txt
workspace_agent-0.1.4.dist-info/RECORD
