Metadata-Version: 2.4
Name: workspace-agent
Version: 0.1.4
Summary: Workspace management package for `workspaces` folder shared between different packages.
Project-URL: Homepage, https://github.com/ppak10/workspace-agent
Project-URL: Issues, https://github.com/ppak10/workspace-agent/issues
Requires-Python: >=3.10
License-File: LICENSE
Requires-Dist: mcp>=1.21.1
Requires-Dist: pydantic>=2.11.9
Requires-Dist: rich>=14.1.0
Requires-Dist: typer>=0.17.4
Dynamic: license-file
